dbops/__init__.py
dbops/_version.py
dbops/influxhelper.py
dbops/sqhelper.py
dbops/timeconverter.py
db_ops-0.1.1.dist-info/LICENSE
db_ops-0.1.1.dist-info/METADATA
db_ops-0.1.1.dist-info/WHEEL
db_ops-0.1.1.dist-info/top_level.txt
db_ops-0.1.1.dist-info/RECORD
