Metadata-Version: 2.1
Name: db-ops
Version: 0.1.1
Summary: UNKNOWN
Home-page: https://github.com/stuianna/DBOps
Author: Stuart Ianna
Author-email: stuian@protonmail.com
License: UNKNOWN
Platform: UNKNOWN
Classifier: Programming Language :: Python :: 3
Classifier: License :: OSI Approved :: MIT License
Classifier: Operating System :: OS Independent
Requires-Python: >=3.6
Requires-Dist: pandas
Requires-Dist: numpy
Requires-Dist: pyrfc3339
Requires-Dist: influxdb
